{
  "filepath": "C:\\Users\\gbonc\\OneDrive\\Desktop\\IA\\AI_colorare_imagini\\uploads\\16672619-6e52-44a4-8f07-a48e02afc4a2_brightness_1759149389.png",
  "original_filepath": "uploads\\16672619-6e52-44a4-8f07-a48e02afc4a2_original.png",
  "history": [
    {
      "name": "Original",
      "filepath": "uploads\\16672619-6e52-44a4-8f07-a48e02afc4a2_original.png",
      "timestamp": 1759149383.371633
    },
    {
      "name": "Colorare AI",
      "filepath": "C:\\Users\\gbonc\\OneDrive\\Desktop\\IA\\AI_colorare_imagini\\uploads\\16672619-6e52-44a4-8f07-a48e02afc4a2_colorized_1759149386.png",
      "timestamp": 1759149386.2317135
    },
    {
      "name": "Filtru Brightness",
      "filepath": "C:\\Users\\gbonc\\OneDrive\\Desktop\\IA\\AI_colorare_imagini\\uploads\\16672619-6e52-44a4-8f07-a48e02afc4a2_brightness_1759149389.png",
      "timestamp": 1759149390.0380776
    }
  ]
}